[
  {
    "id": 1,
    "text": "Hie your friends Damian here",
    "messageType": "Text",
    "imageUrl": "",
    "nextMessageId": 2,
    "option1": "",
    "option1_nextMessageId": "",
    "option2": "",
    "option2_nextMessageId": "",
    "option3": "",
    "option3_nextMessageId": "",
    "option4": "",
    "option4_nextMessageId": "",
    "option5": "",
    "option5_nextMessageId": "",
    "option6": "",
    "option6_nextMessageId": ""
  },
  {
    "id": 2,
    "text": "To know better about  you I ask you some questions ",
    "messageType": "Text",
    "imageUrl": "",
    "nextMessageId": 3,
    "option1": "",
    "option1_nextMessageId": "",
    "option2": "",
    "option2_nextMessageId": "",
    "option3": "",
    "option3_nextMessageId": "",
    "option4": "",
    "option4_nextMessageId": "",
    "option5": "",
    "option5_nextMessageId": "",
    "option6": "",
    "option6_nextMessageId": ""
  },
  {
    "id": 3,
    "text": "Are you comfortable answering them?",
    "messageType": "Question",
    "imageUrl": "",
    "nextMessageId": "",
    "option1": "Yes",
    "option1_nextMessageId": 4,
    "option2": "No",
    "option2_nextMessageId": 9,
    "option3": "",
    "option3_nextMessageId": "",
    "option4": "",
    "option4_nextMessageId": "",
    "option5": "",
    "option5_nextMessageId": "",
    "option6": "",
    "option6_nextMessageId": ""
  },
  {
    "id": 4,
    "text": "How do you get dressed?",
    "messageType": "Question",
    "imageUrl": "",
    "nextMessageId": "",
    "option1": "Standing",
    "option1_nextMessageId": 5,
    "option2": "Sitting",
    "option2_nextMessageId": 5,
    "option3": "In wheelchair",
    "option3_nextMessageId": 5,
    "option4": "on bed",
    "option4_nextMessageId": 5,
    "option5": "",
    "option5_nextMessageId": "",
    "option6": "",
    "option6_nextMessageId": ""
  },
  {
    "id": 5,
    "text": "To what extent do you feel independent in dressing yourself?",
    "messageType": "Question",
    "imageUrl": "",
    "nextMessageId": "",
    "option1": "Independent",
    "option1_nextMessageId": 6,
    "option2": "Partially dependent",
    "option2_nextMessageId": 6,
    "option3": "Completely dependent",
    "option3_nextMessageId": "",
    "option4": "",
    "option4_nextMessageId": ""
  },
  {
    "id": 6,
    "text": "Are there specific types of clothing that you find more comfortable?",
    "messageType": "Question",
    "imageUrl": "",
    "nextMessageId": "",
    "option1": "Loose-fitting clothing",
    "option1_nextMessageId": 7,
    "option2": "Tight fitting",
    "option2_nextMessageId": 7,
    "option3": "both",
    "option3_nextMessageId": 7
  },
  {
    "id": 7,
    "text": "Are there specific features or modifications in clothing that you find particularly helpful?    ",
    "messageType": "Question",
    "imageUrl": "",
    "nextMessageId": "",
    "option1": "Velcro closures",
    "option1_nextMessageId": "8",
    "option2": "Elastic waistbands",
    "option2_nextMessageId": "8",
    "option3": "Magnetic closures",
    "option3_nextMessageId": "8"
  },
  {
    "id": 8,
    "text": "What type of adaptive clothing do you prefer?",
    "messageType": "Question",
    "imageUrl": "",
    "nextMessageId": "",
    "option1": "Upper body clothing with easy-open closures",
    "option1_nextMessageId": 9,
    "option2": "Lower body clothing with elastic or adjustable waistbands",
    "option2_nextMessageId": 9,
    "option3": "Footwear with easy-open closures",
    "option3_nextMessageId": 9,
    "option4": "Undergarments with easy-care features",
    "option4_nextMessageId": 9
  },
  {
    "id": 9,
    "text": "Thank you",
    "messageType": "Text",
    "imageUrl": "",
    "nextMessageId": "",
    "option1": "",
    "option1_nextMessageId": ""
  },
  {
    "id": 10,
    "text": "",
    "messageType": "Text",
    "imageUrl": "",
    "nextMessageId": 8,
    "option1": "",
    "option1_nextMessageId": "",
    "option2": "",
    "option2_nextMessageId": ""
  },
  {
    "id": 11,
    "text": "OpenGenus Quark is the world's first offline search engine.",
    "messageType": "Text",
    "imageUrl": "",
    "nextMessageId": 12,
    "option1": "",
    "option1_nextMessageId": "",
    "option2": "",
    "option2_nextMessageId": ""
  }
]
